.DS_Store
interactions/ext/transcript/__init__.py
interactions/ext/transcript/cache.py
interactions/ext/transcript/emoji_convert.py
interactions/ext/transcript/transcript.py
interactions/ext/transcript/utils.py
interactions/ext/transcript/html/base.html
interactions/ext/transcript/html/attachment/audio.html
interactions/ext/transcript/html/attachment/image.html
interactions/ext/transcript/html/attachment/message.html
interactions/ext/transcript/html/attachment/video.html
interactions/ext/transcript/html/component/component_button.html
interactions/ext/transcript/html/component/component_menu.html
interactions/ext/transcript/html/component/component_menu_options.html
interactions/ext/transcript/html/component/component_menu_options_emoji.html
interactions/ext/transcript/html/embed/author.html
interactions/ext/transcript/html/embed/author_icon.html
interactions/ext/transcript/html/embed/body.html
interactions/ext/transcript/html/embed/description.html
interactions/ext/transcript/html/embed/field-inline.html
interactions/ext/transcript/html/embed/field.html
interactions/ext/transcript/html/embed/footer.html
interactions/ext/transcript/html/embed/footer_image.html
interactions/ext/transcript/html/embed/image.html
interactions/ext/transcript/html/embed/thumbnail.html
interactions/ext/transcript/html/embed/title.html
interactions/ext/transcript/html/message/content.html
interactions/ext/transcript/html/message/message.html
interactions/ext/transcript/html/message/meta.html
interactions/ext/transcript/html/message/pin.html
interactions/ext/transcript/html/message/reference.html
interactions/ext/transcript/html/message/reference_unknown.html
interactions/ext/transcript/html/message/start.html
interactions/ext/transcript/html/message/thread.html
interactions/ext/transcript/html/reaction/custom_emoji.html
interactions/ext/transcript/html/reaction/emoji.html
interactions/ext/transcript/html/script/fancy_time.html
interactions_transcript-0.0.4.dist-info/LICENSE
interactions_transcript-0.0.4.dist-info/METADATA
interactions_transcript-0.0.4.dist-info/WHEEL
interactions_transcript-0.0.4.dist-info/top_level.txt
interactions_transcript-0.0.4.dist-info/RECORD
