Metadata-Version: 2.1
Name: interactions-transcript
Version: 0.0.4
Summary: An extension library for interactions.py to create transcripts.
Home-page: https://github.com/ItsRqtl/interactions-transcript
Author: ItsRqtl
Author-email: itsrqtl@gmail.com
License: MIT
Classifier: Programming Language :: Python :: 3
Classifier: Development Status :: 4 - Beta
Classifier: License :: OSI Approved :: MIT License
Classifier: Operating System :: OS Independent
Requires-Python: >=3.8.6
License-File: LICENSE
Requires-Dist: discord-py-interactions (>=4.3.2)
Requires-Dist: pytz
Requires-Dist: pandas
Requires-Dist: grapheme
Requires-Dist: emoji
